sprockets.cli-0.1.0-py2.7-nspkg.pth
sprockets.cli-0.1.0.dist-info/RECORD
sprockets.cli-0.1.0.dist-info/WHEEL
sprockets.cli-0.1.0.dist-info/metadata.json
sprockets.cli-0.1.0.dist-info/DESCRIPTION.rst
sprockets.cli-0.1.0.dist-info/METADATA
sprockets.cli-0.1.0.dist-info/entry_points.txt
sprockets.cli-0.1.0.dist-info/top_level.txt
sprockets.cli-0.1.0.dist-info/namespace_packages.txt
sprockets/cli/__init__.py
