Metadata-Version: 2.0
Name: sprockets.cli
Version: 0.1.0
Summary: Sprockets command line application runner
Home-page: https://github.com/sprockets/sprockets.cli
Author: AWeber Communications
Author-email: UNKNOWN
License: Copyright (c) 2014 AWeber Communications
